sphinx_opensearch/__init__.py
sphinx_opensearch/sphinxsearch.py
sphinx_opensearch/common/__init__.py
sphinx_opensearch/common/clients.py
sphinx_opensearch-0.4.0.dist-info/AUTHORS
sphinx_opensearch-0.4.0.dist-info/LICENSE
sphinx_opensearch-0.4.0.dist-info/METADATA
sphinx_opensearch-0.4.0.dist-info/WHEEL
sphinx_opensearch-0.4.0.dist-info/entry_points.txt
sphinx_opensearch-0.4.0.dist-info/pbr.json
sphinx_opensearch-0.4.0.dist-info/top_level.txt
sphinx_opensearch-0.4.0.dist-info/RECORD
