Metadata-Version: 2.1
Name: sphinx-opensearch
Version: 0.4.0
Summary: Python program to index Sphinx-based documentations into Elasticsearch or Opensearch
Home-page: https://github.com/opentelekomcloud/sphinx-opensearch
Author: Open Telekom Cloud - Ecosystem Squad
Author-email: dl-pbcotcdeleco@t-systems.com
License: UNKNOWN
Keywords: Sphinx, search, python
Platform: UNKNOWN
Classifier: License :: OSI Approved :: Apache Software License
Classifier: Operating System :: POSIX :: Linux
Classifier: Operating System :: Unix
Classifier: Operating System :: MacOS
Classifier: Programming Language :: Python
Classifier: Programming Language :: Python :: 2
Classifier: Programming Language :: Python :: 2.7
Classifier: Programming Language :: Python :: 3
Classifier: Programming Language :: Python :: 3.6
Classifier: Programming Language :: Python :: 3.7
License-File: LICENSE
Requires-Dist: bs4
Requires-Dist: lxml
Requires-Dist: opensearch-py
Requires-Dist: elasticsearch
